clickthroughs/__init__.py
clickthroughs/admin.py
clickthroughs/apps.py
clickthroughs/models.py
clickthroughs/urls.py
clickthroughs/views.py
clickthroughs/migrations/0001_initial.py
clickthroughs/migrations/0002_clickthrough_hostname_clickthrough_session_id_and_more.py
clickthroughs/migrations/0003_campaign_platform_campaignhostname_and_more.py
clickthroughs/migrations/0004_remove_campaign_suppliers_campaign_parameters_and_more.py
clickthroughs/migrations/__init__.py
clickthroughs/templatetags/__init__.py
clickthroughs/templatetags/click_tags.py
django_clickthroughs-0.1.dist-info/METADATA
django_clickthroughs-0.1.dist-info/WHEEL
django_clickthroughs-0.1.dist-info/licenses/LICENSE
django_clickthroughs-0.1.dist-info/RECORD
